{
  "users": [
    {
      "name": "Juliet Omawww",
      "email": "julie@yahoo.comwwww",
      "number": "08100000000ww",
      "id": "1"
    },
    {
      "id": "2",
      "name": "James Williams",
      "email": "jameswilly@gmail.com",
      "number": "08111111111"
    },
    {
      "id": "3",
      "name": "Ahmed Ali",
      "email": "ahmedali012@gmail.com",
      "number": "09022222222"
    },
    {
      "name": "Bekmurrod",
      "email": "gracefunsho@gmail.com",
      "number": "09033333333",
      "id": "4"
    },
    {
      "id": "1392",
      "name": "Ziyodbek Ziyod",
      "email": "ziyodyakubov23@gmail.com",
      "number": "8903921072"
    }
  ]
}